MULTIPLEXER/multiplexer.vhdl
library ieee;
use ieee.std_logic_1164.all;

ENTITY mux is 
    port(
        a,b: in STD_LOGIC_VECTOR (7 DOWNTO 0);
        sel: in bit_vector (1 downto 0);
        c : out STD_LOGIC_VECTOR (7 DOWNTO 0)
    );
END mux;

ARCHITECTURE example of mux is 

begin 

process (a,b,sel) 
begin
    IF(sel = "00") THEN
        c <= "00000000";
    ELSIF(sel = "01") THEN
        c <= a;
    ELSIF(sel = "10") THEN
        c <= b;
    ELSE 
        c <= (others =>'Z');
    END IF;
end process;

end example;

MULTIPLEXER/tb.vhdl
library ieee;
use ieee.std_logic_1164.all;

ENTITY TB is end TB;


ARCHITECTURE TB of TB is 

signal A, B,C: std_logic_vector(7 downto 0);
signal sel: bit_vector(1 downto 0);

component mux is 
    port(
        A,B: in std_logic_vector(7 downto 0);
        sel: in bit_vector (1 downto 0);

        C: out std_logic_vector(7 downto 0)
    );
end component;
BEGIN

DUT:mux port map (
    A => A,
    B => B,
    C => C,
    sel => sel
);

stimulus: PROCESS begin
    
    -- testing 00 selection (Null selection, C = "000000");
    sel <= "00";
    FOR i in 0 to 7 LOOP -- foor loop, to produce variable input on A and B
        A <= (others => '0');
        A(i) <= '1';
        
        B <= (others => '0');
        B(7 - i) <= '1';
        wait for 1 ns;
        assert C = "00000000" report "error in test: sel(00) C = 0"; 
    end loop;
    
    -- testing 01 selection (A input on C output)
    sel <= "01";
    FOR i in 0 to 7 LOOP -- foor loop to produce variable input on A and B
        A <= (others => '0');
        A(i) <= '1';
        
        B <= (others => '0');
        B(7 - i) <= '1';
        wait for 1 ns;
        assert C = A report "error in test: sel(01) C = A"; 
    end loop;
    
    -- testing selection 10 (B input on C output)
    sel <= "10";
    FOR i in 0 to 7 LOOP -- foor loop, to produce variable signal on input
        A <= (others => '0');
        A(i) <= '1';
        
        B <= (others => '0');
        B(7 - i) <= '1';
        wait for 1 ns;
        assert C = B report "error in test: sel(10) C = B"; 
    end loop;
    
    -- testing 11 selection, High impedance (Z) 
    sel <= "11";
    FOR i in 0 to 7 LOOP -- foor loop, using attribute range of A to iterate
        A <= (others => '0');
        A(i) <= '1';
        
        B <= (others => '0');
        B(7 - i) <= '1';
        wait for 1 ns;
        assert C = "ZZZZZZZZ" report "error in test: sel(11) C = Z"; 
    end loop;


    wait; --ending process
end process;



END;

MULTIPLEXER/wave.vcd
$date
  Sat Apr 19 21:57:02 2025
$end
$version
  GHDL v0
$end
$timescale
  1 ns
$end
$scope module standard $end
$upscope $end
$scope module std_logic_1164 $end
$upscope $end
$scope module tb $end
$var reg 8 ! a[7:0] $end
$var reg 8 " b[7:0] $end
$var reg 8 # c[7:0] $end
$var reg 2 $ sel[1:0] $end
$scope module dut $end
$var reg 8 % a[7:0] $end
$var reg 8 & b[7:0] $end
$var reg 2 ' sel[1:0] $end
$var reg 8 ( c[7:0] $end
$upscope $end
$upscope $end
$enddefinitions $end
#0
b00000001 !
b10000000 "
b00000000 #
b00 $
b00000001 %
b10000000 &
b00 '
b00000000 (
#1000000
b00000010 !
b01000000 "
b00000010 %
b01000000 &
#2000000
b00000100 !
b00100000 "
b00000100 %
b00100000 &
#3000000
b00001000 !
b00010000 "
b00001000 %
b00010000 &
#4000000
b00010000 !
b00001000 "
b00010000 %
b00001000 &
#5000000
b00100000 !
b00000100 "
b00100000 %
b00000100 &
#6000000
b01000000 !
b00000010 "
b01000000 %
b00000010 &
#7000000
b10000000 !
b00000001 "
b10000000 %
b00000001 &
#8000000
b00000001 !
b10000000 "
b00000001 #
b01 $
b00000001 %
b10000000 &
b01 '
b00000001 (
#9000000
b00000010 !
b01000000 "
b00000010 #
b00000010 %
b01000000 &
b00000010 (
#10000000
b00000100 !
b00100000 "
b00000100 #
b00000100 %
b00100000 &
b00000100 (
#11000000
b00001000 !
b00010000 "
b00001000 #
b00001000 %
b00010000 &
b00001000 (
#12000000
b00010000 !
b00001000 "
b00010000 #
b00010000 %
b00001000 &
b00010000 (
#13000000
b00100000 !
b00000100 "
b00100000 #
b00100000 %
b00000100 &
b00100000 (
#14000000
b01000000 !
b00000010 "
b01000000 #
b01000000 %
b00000010 &
b01000000 (
#15000000
b10000000 !
b00000001 "
b10000000 #
b10000000 %
b00000001 &
b10000000 (
#16000000
b00000001 !
b10000000 "
b10 $
b00000001 %
b10000000 &
b10 '
#17000000
b00000010 !
b01000000 "
b01000000 #
b00000010 %
b01000000 &
b01000000 (
#18000000
b00000100 !
b00100000 "
b00100000 #
b00000100 %
b00100000 &
b00100000 (
#19000000
b00001000 !
b00010000 "
b00010000 #
b00001000 %
b00010000 &
b00010000 (
#20000000
b00010000 !
b00001000 "
b00001000 #
b00010000 %
b00001000 &
b00001000 (
#21000000
b00100000 !
b00000100 "
b00000100 #
b00100000 %
b00000100 &
b00000100 (
#22000000
b01000000 !
b00000010 "
b00000010 #
b01000000 %
b00000010 &
b00000010 (
#23000000
b10000000 !
b00000001 "
b00000001 #
b10000000 %
b00000001 &
b00000001 (
#24000000
b00000001 !
b10000000 "
bZZZZZZZZ #
b11 $
b00000001 %
b10000000 &
b11 '
bZZZZZZZZ (
#25000000
b00000010 !
b01000000 "
b00000010 %
b01000000 &
#26000000
b00000100 !
b00100000 "
b00000100 %
b00100000 &
#27000000
b00001000 !
b00010000 "
b00001000 %
b00010000 &
#28000000
b00010000 !
b00001000 "
b00010000 %
b00001000 &
#29000000
b00100000 !
b00000100 "
b00100000 %
b00000100 &
#30000000
b01000000 !
b00000010 "
b01000000 %
b00000010 &
#31000000
b10000000 !
b00000001 "
b10000000 %
b00000001 &
